{
 "meta": {
  "id": "node_pilot_1",
  "title": "노드 설명 파일럿 43 (한 줄 공간묘사·NPC금지)"
 },
 "items": [
  {
   "n": 3,
   "kind": "elite",
   "loc": "마그마 핵 · triflower/elite  | 지난코멘트: 화산의 최심부. 잠시 서있는 것만으로도 버티기 힘들 정도의 기온이다.",
   "text": "분화구 가장 깊은 자리. 마그마가 뭉텅이로 끓어오른다. 가장 강한 화염 아인이 여기 머문다.",
   "proposal": "화산의 최심부. 잠시 서 있는 것만으로도 버티기 힘든 열기다."
  },
  {
   "n": 10,
   "kind": "combat",
   "loc": "하나브릿지 · lar-forest/combat  | 지난코멘트: 지역 설명은 반드시 한 줄만. ~돌다리 까지만 하면 완벽.",
   "text": "일루네온과 라르 숲을 잇는 돌다리. 다리 밑에서 그림자 강아지가 으르렁댄다.",
   "proposal": "일루네온과 라르 숲을 잇는 돌다리."
  },
  {
   "n": 15,
   "kind": "combat",
   "loc": "발전실 · enicham/combat  | 지난코멘트: 표현 자체가 어색합니다.",
   "text": "안쪽 발전실. 코일이 낮게 웅웅거리는 소리가 방을 채운다. 가끔 스파크가 튄다.",
   "proposal": "발전소 안쪽의 발전실. 굵은 코일이 줄지어 늘어서 있다."
  },
  {
   "n": 16,
   "kind": "gather",
   "loc": "임페리시아 흔적 · tacomi/gather  | 지난코멘트: 공간에 대해 설명해야지, 이것은 이미 돌입한 모험가의 경험입니다.",
   "text": "홀로그램 필드 가장자리에 임페리시아의 흔적이 희미하게 남아 있다.",
   "proposal": "홀로그램 필드 가장자리. 빛 입자가 희미하게 떠다닌다."
  },
  {
   "n": 17,
   "kind": "event",
   "loc": "동문 · iluneon/event  | 지난코멘트: 바람이 길게 흐른다는 표현은 어색.",
   "text": "일루네온 동쪽 문. 라르 숲 방향으로 바람이 길게 흐른다.",
   "proposal": "라르 숲으로 이어지는 일루네온 동쪽 문."
  },
  {
   "n": 19,
   "kind": "event",
   "loc": "서문 · iluneon/event",
   "text": "일루네온 서쪽 문. 알리메스 방향으로 안개가 길게 흐른다.",
   "proposal": "알리메스로 이어지는 일루네온 서쪽 문."
  },
  {
   "n": 20,
   "kind": "village",
   "loc": "일루네온 광장 · iluneon/village  | 지난코멘트: 중심도 아니고, 이유르 얘기도 하지 마세요. 단지 일루네온의 풍경을 묘사하면 됩니다.",
   "text": "컬러즈 세계의 중심. 분수대 옆에서 어린 소년 니아 이유르 가 잠시 멈춰 있다. 그가 그대를 본다. \"왔군요.\"",
   "proposal": "분수대를 둘러싼 너른 광장. 사방으로 골목이 뻗어 있다."
  },
  {
   "n": 23,
   "kind": "combat",
   "loc": "주술 연습실 · luna/combat  | 지난코멘트: 이름이 바뀌었을거고, 주문을 두고 갔다는 표현은 없습니다.",
   "text": "실습홀 옆의 주술 연습실. 누군가 주문을 그대로 두고 갔다.",
   "proposal": "마법 학교 안쪽의 주술 연습실. 벽마다 낡은 주문서가 붙어 있다."
  },
  {
   "n": 30,
   "kind": "activity",
   "loc": "르슈드 분기 · reshud/activity  | 지난코멘트: 좋은데 앞의 마을 이름 4개는 세계 각지를~ 로 바꿔 주세요.",
   "text": "알리메스·일루네온·리아그랄타·풍혈지대를 잇는 교차로. 마차 정거장에서 작은 종이 울린다.",
   "proposal": "세계 각지를 잇는 작은 마차 교차로. 정거장에서 종이 울린다."
  },
  {
   "n": 31,
   "kind": "combat",
   "loc": "리아그랄타 평원 · riagralta/combat  | 지난코멘트: 이런 식으로 몬스터 이름을 적었다간 몬스터 이름이 변경될 때 raid가 깨질 겁니다.",
   "text": "일루네온 북쪽으로 끝없이 펼쳐진 초원. 양 떼 너머에서 그림자 늑대가 보인다. 서쪽으로 초원 교역소의 천막이 늘어선다.",
   "proposal": "일루네온 북쪽으로 끝없이 펼쳐진 초원. 멀리 번개 구름이 인다."
  },
  {
   "n": 34,
   "kind": "village",
   "loc": "풍혈지대 · demon-windfall/village  | 지난코멘트: NPC를 등장시키지 마세요. 앞에서 비슷한 얘기를 했습니다.",
   "text": "강한 바람이 끊임없이 불어치는 계곡. 일루네온·리아그랄타에서 타코미로 넘어가는 길목. 리엔카이가 밤참새 노래를 흥얼거린다.",
   "proposal": "강한 바람이 끊임없이 몰아치는 계곡. 타코미로 넘어가는 길목이다."
  },
  {
   "n": 37,
   "kind": "region",
   "loc": "마틴 항 · 키시나 해변 · /region  | 지난코멘트: 화살표를 설명문에 쓰지 마세요.",
   "text": "일루네온과 클러치 사이의 항구. 마틴 → 배 → 클러치. 키시나 해변 분기.",
   "proposal": "일루네온과 클러치 사이의 항구. 배를 갈아타는 길목이며, 키시나 해변으로도 갈라진다."
  },
  {
   "n": 87,
   "kind": "rest",
   "loc": "안마당 · alimes/rest  | 지난코멘트: 옅게 삭제.",
   "text": "마을 구석의 작은 안마당. 안개가 돌 위에 옅게 깔린다.",
   "proposal": "마을 구석의 작은 안마당. 안개가 돌 위에 깔린다."
  },
  {
   "n": 96,
   "kind": "rest",
   "loc": "골짜기 쉼터 · diropel/rest  | 지난코멘트: 바람 얘기는 빼죠.",
   "text": "부족 마을 안쪽 골짜기. 폭신한 풀 위에 딜롭 아이들이 둥글게 누워 잔다. 바람도 둥글게 분다.",
   "proposal": "딜롭 부족 마을 안쪽의 아늑한 골짜기. 폭신한 풀밭이 펼쳐져 있다."
  },
  {
   "n": 104,
   "kind": "gather",
   "loc": "둥지 꼭대기 · falcon-garden/gather  | 지난코멘트: 살아~ 부터 제거.",
   "text": "군도 가장 깊은 둥지. 바람과 깃털이 뭉쳐 굳어 있다. 살아 내려간 자에게만 큰 것이 남는다.",
   "proposal": "군도에서 가장 깊은 둥지. 바람과 깃털이 뭉쳐 굳어 있다."
  },
  {
   "n": 106,
   "kind": "elite",
   "loc": "금단의 회랑 · demon-castle/elite  | 지난코멘트: 곳 까지만. 마왕성의 비밀을 실제로 작성하는 AI가 모를 것 같아서요.",
   "text": "마왕성 깊은 곳. 옛 봉인의 문이 잠겨 있다.",
   "proposal": "마왕성 깊은 곳."
  },
  {
   "n": 108,
   "kind": "gather",
   "loc": "식료 저장고 · iluneon/gather",
   "text": "식당 옆 시원한 저장고. 빈 자리에 작은 것들이 가지런히 놓여 있다.",
   "proposal": "식당 옆의 시원한 저장고. 식재료가 가지런히 쌓여 있다."
  },
  {
   "n": 109,
   "kind": "rest",
   "loc": "의뢰 대기실 · iluneon/rest",
   "text": "길드 안쪽의 대기실. 의자에 손님 몇이 앉아 있다. 차 한 잔이 식어 있다.",
   "proposal": "길드 안쪽의 조용한 대기실. 푹신한 의자가 놓여 있다."
  },
  {
   "n": 119,
   "kind": "boss",
   "loc": "타마모와의 장난 · manonickla/boss  | 지난코멘트: 표현은 괜찮은데 마노니클라에 타마모가 있었나요?  ※ 확인필요: 타마모가 마노니클라 권역이 맞는지(코멘트 의문)",
   "text": "노을 아래 구미호 한 마리가 꼬리를 빙 두르고 앉아, 이쪽을 보며 빙긋 웃는다.",
   "proposal": "구미호 한 마리가 꼬리를 두르고 앉아, 이쪽을 보며 빙긋 웃는다."
  },
  {
   "n": 126,
   "kind": "boss",
   "loc": "티프레와의 겨룸 · oldshrine/boss  | 지난코멘트: 예복을 입고 있더라도 그걸로 묘사할 캐릭터가 아닙니다 (이전에 얘기했죠)",
   "text": "티프레가 예복 자락을 가다듬고 곧게 일어선다. 정전기가 빛 무늬를 따라 잘게 번진다.",
   "proposal": "호랑이 신수가 호기심 어린 눈으로 이쪽을 바라본다. 빛 무늬를 따라 정전기가 잘게 번진다."
  },
  {
   "n": 131,
   "kind": "elite",
   "loc": "사냥터 한복판 · yusezria/elite  | 지난코멘트: \"가장 강한 것이 여기~\" 이거, 엘리트 얘기인가요? 다른 곳에서도 전부 빼고, 필요하면 다른 표현을 제시하겠습니다.",
   "text": "철과 물이 같은 공간에서 부딪히는 자리. 가장 강한 것이 여기 머문다.",
   "proposal": "철과 물의 기운이 뒤엉켜 고인 자리."
  },
  {
   "n": 216,
   "kind": "combat",
   "loc": "클러치 상륙장 · moss-south/combat  | 지난코멘트: 무엇<- 이 표현 전부 제거.",
   "text": "극동 항로의 종점. 파도 사이에서 물에 잠긴 무엇이 떠오른다.",
   "proposal": "극동 항로의 종점. 파도가 부두에 부딪힌다."
  },
  {
   "n": 217,
   "kind": "event",
   "loc": "등대 · moss-north/event  | 지난코멘트: 불빛이 돈다는게 전혀 호응이 맞지 않음",
   "text": "부두 끝의 낡은 등대. 불빛이 일정한 간격으로 돈다. 수평선 위로 팔콘 가든 공중 군도가 떠 있다.",
   "proposal": "부두 끝의 낡은 등대. 수평선 너머로 팔콘 가든 공중 군도가 떠 있다."
  },
  {
   "n": 238,
   "kind": "combat",
   "loc": "시장 뒷골목 · iluneon/combat",
   "text": "가판 뒤 좁은 그늘. 누군가 바닥에 무엇을 흘려 놓았다.",
   "proposal": "가판 뒤로 난 좁고 그늘진 골목."
  },
  {
   "n": 239,
   "kind": "event",
   "loc": "종지기 골방 · iluneon/event",
   "text": "시계탑 아래 종지기 노인이 머무는 작은 방. 종 줄이 천장으로 길게 올라간다.",
   "proposal": "시계탑 아래의 작은 방. 종 줄이 천장으로 길게 이어진다."
  },
  {
   "n": 240,
   "kind": "activity",
   "loc": "환전소 · iluneon/activity",
   "text": "시장 한 모퉁이의 작은 환전소. 동전 부딪히는 소리가 또렷이 떨어진다.",
   "proposal": "시장 모퉁이의 작은 환전소. 동전 더미가 칸칸이 쌓여 있다."
  },
  {
   "n": 241,
   "kind": "combat",
   "loc": "시계 회랑 · iluneon/combat",
   "text": "시계탑 안의 좁은 회랑. 톱니바퀴 소리가 또박또박 걸음을 맞춰 온다.",
   "proposal": "시계탑 안쪽의 좁은 회랑. 톱니바퀴 소리가 끊이지 않는다."
  },
  {
   "n": 242,
   "kind": "shop",
   "loc": "잡화점 · iluneon/shop",
   "text": "시장 끝의 잡화 가게. 물건마다 떨어지는 속도가 다르다.",
   "proposal": "시장 끝의 자그마한 잡화 가게. 온갖 물건이 빼곡하다."
  },
  {
   "n": 243,
   "kind": "combat",
   "loc": "식당 뒷골목 · iluneon/combat",
   "text": "식당 뒤 기름 떨어진 좁은 길. 좁은 담벼락 사이에서 그림자가 어른거린다.",
   "proposal": "식당 뒤편의 좁고 어두운 길."
  },
  {
   "n": 244,
   "kind": "rest",
   "loc": "여관 안마당 · iluneon/rest",
   "text": "식당 옆 작은 여관의 안마당. 노을이 마당 돌 위에 오래 남는다.",
   "proposal": "식당 옆 여관의 아담한 안마당."
  },
  {
   "n": 245,
   "kind": "event",
   "loc": "첨탑 그늘 · iluneon/event",
   "text": "시계탑 그림자가 광장 바닥을 가로지르는 자리. 그림자 끝이 조금씩 어긋나 있다.",
   "proposal": "시계탑 그늘이 길게 드리운 광장 한켠."
  },
  {
   "n": 246,
   "kind": "gather",
   "loc": "첨탑 옥상 · iluneon/gather  | 지난코멘트: 정상 이후로 문장이 모두 어색.",
   "text": "시계탑 정상. 바람이 느릿느릿 분다. 옥상 가장자리에 작은 시간의 조각이 떨어져 있다.",
   "proposal": "시계탑 꼭대기의 좁은 옥상. 바람이 거세다."
  },
  {
   "n": 247,
   "kind": "combat",
   "loc": "거리 모서리 · iluneon/combat",
   "text": "광장에서 시장으로 빠지는 모서리. 그림자가 벽 쪽에 붙어 움직이지 않는다.",
   "proposal": "광장에서 시장으로 빠지는 길모퉁이."
  },
  {
   "n": 248,
   "kind": "event",
   "loc": "일루네온 시계탑 · iluneon/event  | 지난코멘트: 첨탑 까지만.",
   "text": "도시의 가장 높은 첨탑. 시계 뒷면에서 시간 축의 미세한 어긋남이 보인다.",
   "proposal": "도시에서 가장 높은 첨탑."
  },
  {
   "n": 249,
   "kind": "gather",
   "loc": "일루네온 식당 · iluneon/gather",
   "text": "모험가들이 끼니를 때우는 곳. 구석 자리에 인형 같은 소녀가 멍하니 앉아 있다 임페리시아.",
   "proposal": "모험가들이 끼니를 때우는 식당."
  },
  {
   "n": 250,
   "kind": "activity",
   "loc": "일루네온 길드 본부 · iluneon/activity  | 지난코멘트: 특정한 NPC를 등장시키지 마세요. 특정한 사람의 행동도 묘사하지 마세요. 노드를 지역으로 표현할 때 누군가의 행동을 표현하는 건 너무 짧은 시간 프레임 안의 묘사입니다.",
   "text": "의뢰 게시판 앞에서 사람들이 분주하다. 인간 모험가 하코가 게시판을 노려본다.",
   "proposal": "의뢰 게시판이 늘 붐비는 길드 본부."
  },
  {
   "n": 251,
   "kind": "shop",
   "loc": "일루네온 시장 · iluneon/shop",
   "text": "마법 상점·식료 가판이 줄지어 선 골목. 사천왕 중 하나가 평민 행세를 하며 어슬렁댄다.",
   "proposal": "마법 상점과 식료 가판이 줄지어 선 골목."
  },
  {
   "n": 254,
   "kind": "combat",
   "loc": "키시나 진입로 · martin/combat  | 지난코멘트: 진입로 -> 마틴 남쪽의 모래사장 입구.",
   "text": "마틴 남쪽으로 모래가 깔린 진입로. 파도 소리가 일정하게 밀려온다.",
   "proposal": "마틴 남쪽의 모래사장 입구. 파도 소리가 일정하게 밀려온다."
  },
  {
   "n": 325,
   "kind": "combat",
   "loc": "오드 능선 · riagralta/combat  | 지난코멘트: 산비탈을 따라 만들어진 능선. 수평선 너머로 시퍼런 공기가 보인다.",
   "text": "산비탈 위 능선. 바람이 살갗을 길게 스친다. 능선 너머로 유스제리아의 무거운 공기가 깔린다.",
   "proposal": "산비탈을 따라 만들어진 능선. 수평선 너머로 시퍼런 공기가 보인다."
  },
  {
   "n": 329,
   "kind": "combat",
   "loc": "신전 문터 · oldshrine/combat  | 지난코멘트: 타코미 뒷편의 위험한 거리. 아무렇게나 버려진 철제 구조물에 전기가 통하고 있는 것 같다.",
   "text": "타코미 가도 너머 부서진 신전 문터. 기둥이 비스듬히 서 있고, 정전기가 드문드문 튄다.",
   "proposal": "타코미 뒷편의 위험한 거리. 아무렇게나 버려진 철제 구조물에 전기가 통하고 있는 것 같다."
  },
  {
   "n": 343,
   "kind": "combat",
   "loc": "카페 골목 · tacomi/combat  | 지난코멘트: 커피 가게가 늘어서 있다.",
   "text": "타코미의 낮 골목. 라테 잔이 나란히 놓여 있다.",
   "proposal": "커피 가게가 늘어선 골목."
  },
  {
   "n": 351,
   "kind": "village",
   "loc": "초원 교역소 · tradepost/village  | 지난코멘트: npc 출연시키지 마세요.",
   "text": "리아그랄타 초원 서쪽 천막이 늘어선 대상 교역지. 라미아 상인 사라사가 직물과 향신료를 펼친 채, 긴 꼬리를 둥글게 말고 손님을 맞는다.",
   "proposal": "리아그랄타 초원 서쪽, 천막이 늘어선 대상 교역지."
  },
  {
   "n": 355,
   "kind": "elite",
   "loc": "트리플라워 화산 · triflower/elite  | 지난코멘트: 활화산 까진 좋았는데, 그 뒤는 삭제. 100년 전에 마지막으로 분화했다고 한다 정도로.",
   "text": "라르 숲과 모스 사이의 활화산. 분화구에서 화염 아인들이 일어서고, 위쪽 둥지에 화염 아라크네가 실을 친다.",
   "proposal": "활화산. 100년 전에 마지막으로 분화했다고 한다."
  }
 ]
}